promdens/__init__.py
promdens/promdens.py
promdens-1.0.0.dist-info/METADATA
promdens-1.0.0.dist-info/WHEEL
promdens-1.0.0.dist-info/entry_points.txt
promdens-1.0.0.dist-info/licenses/LICENSE
promdens-1.0.0.dist-info/RECORD
