Metadata-Version: 2.3
Name: promdens
Version: 1.0.0
Summary: Promoted Density Approach for sampling initial conditions for trajectory-based nonadiabatic photodynamics
Project-URL: Homepage, https://github.com/PHOTOX/promdens
Project-URL: Documentation, https://github.com/PHOTOX/promdens/blob/main/README.md
Project-URL: Repository, https://github.com/PHOTOX/promdens.git
Project-URL: Issues, https://github.com/PHOTOX/promdens/issues
Author-email: Jiri Janos <jiri.janos98@gmail.com>, Daniel Hollas <danekhollas@gmail.com>
License: MIT License
License-File: LICENSE
Classifier: Development Status :: 5 - Production/Stable
Classifier: License :: OSI Approved :: MIT License
Classifier: Programming Language :: Python
Classifier: Programming Language :: Python :: 3 :: Only
Classifier: Topic :: Scientific/Engineering
Requires-Python: >=3.7
Requires-Dist: matplotlib~=3.0
Requires-Dist: numpy>=1.15
Provides-Extra: tests
Requires-Dist: inline-snapshot!=0.13.2,>=0.9; extra == 'tests'
Requires-Dist: pytest>=7.4; extra == 'tests'
